socratautil/__init__.py
socratautil/socratautil.py
atd_socrata_util_dev-0.0.10.dist-info/LICENSE
atd_socrata_util_dev-0.0.10.dist-info/METADATA
atd_socrata_util_dev-0.0.10.dist-info/WHEEL
atd_socrata_util_dev-0.0.10.dist-info/top_level.txt
atd_socrata_util_dev-0.0.10.dist-info/RECORD
