Metadata-Version: 2.1
Name: atd-socrata-util-dev
Version: 0.0.10
Summary: Utilities interacting with the Socrata Open Data API.
Home-page: https://github.com/cityofaustin/atd-data-utilities/tree/master/atd-socrata-util
Author: City of Austin
Author-email: transportation.data@austintexas.gov
License: UNKNOWN
Platform: UNKNOWN
Classifier: Programming Language :: Python :: 3
Classifier: License :: Public Domain
Classifier: Operating System :: OS Independent
Classifier: Development Status :: 4 - Beta
Requires-Dist: requests
Requires-Dist: atd-data-util
